{
    "items":[
      
    
      {
         "category": ""
      },
        {
          
           "image": "",          
           "name": "",
           "description": "",
           "meal_price": "7",
           "available": true,
            "popular_item": false,
            "tags":100
        },
        
        {
          
           "image": "",          
           "name": "risotto",
           "description": "",
           "meal_price": "9",
           "available": true,
           "popular_item": true,
            "tags":101
        },
      
      {
         "category": ""
      },
      {
       "image":"",
          "name": "",
          "description": "",
           "meal_price": "7",
           "available": true,
          "popular_item": true,
          "tags":102
          
         }
   
      ]
    }

